{
    "members": [
       {
           "name": "Cracky Koksberg",
           "rank": "13♛ Real-OG",
           "highlight": true,
           "picture": "https://www.goldphoenix.de/wcf/images/avatars/3c/10969-3ca2cb4fa6ac197c2c08efbf8e6c7f78176eca95.webp",
           "profile": "https://www.goldphoenix.de/wcf/index.php?user/2240-peppschnueffler/"
       },
       {
           "name": "Albert Reznov",
           "rank": "12♛ OG",
           "highlight": true,
           "picture": "https://www.goldphoenix.de/wcf/images/avatars/29/8203-29b7f985c31fc7a982c555fca4a640bb04dc191c.webp",
           "profile": "https://www.goldphoenix.de/wcf/index.php?user/2305-stoney/"
       },
       {
           "name": "Apple Danger",
           "rank": "11♛ Hood-Boss",
           "highlight": false,
           "picture": "https://www.goldphoenix.de/wcf/images/avatars/c9/12588-c916bbce4180ba3002a15cd008463bcca59ea090.webp",
           "profile": "https://www.goldphoenix.de/wcf/index.php?user/2282-apple-ace/"
       },
       {
           "name": "Maxi Reznov",
           "rank": "8♛ Instruktor",
           "highlight": false,
           "picture": "https://www.goldphoenix.de/wcf/images/avatars/c3/6983-c3f5d1de1557659bddd04fed9603d74a68bf7597.jpg",
           "profile": "https://www.goldphoenix.de/wcf/index.php?user/1537-maxi-esser/"
       },
       {
           "name": "Khabib Sokolow",
           "rank": "8♛ Instruktor",
           "highlight": false,
           "picture": "https://www.goldphoenix.de/wcf/images/avatars/a0/10881-a074df72266742cfbcfec7a1989d37a740f3222e.webp",
           "profile": "https://www.goldphoenix.de/wcf/index.php?user/1590-khabib/"
       },
       {
           "name": "Szyroi Ace",
           "rank": "5♛ Baller",
           "highlight": false,
           "picture": "https://www.goldphoenix.de/wcf/images/avatars/53/14572-53344dcc009f7476eed76eae5041f02b61de81f0.jpg",
           "profile": "https://www.goldphoenix.de/wcf/index.php?user/2476-szyroi/"
        },
        {
           "name": "Nick Santos",
           "rank": "5♛ Baller",
           "highlight": false,
           "picture": "https://www.goldphoenix.de/wcf/images/avatars/5d/7248-5ddf1a14be6a01af55a682ea178727ea320839d1.webp",
           "profile": "https://www.goldphoenix.de/wcf/index.php?user/2330-santos/"
        },
        {
           "name": "Tristen Harrison",
           "rank": "5♛ Baller",
           "highlight": false,
           "picture": "https://www.goldphoenix.de/wcf/images/avatars/d2/6588-d2e63f66d1354d1c231ddbe53ffa899bb109f7df.gif",
           "profile": "https://www.goldphoenix.de/wcf/index.php?user/2027-tristano/"
        },
        {
           "name": "Sebastian Feinstaub",
           "rank": "5♛ Baller",
           "highlight": false,
           "picture": "https://i.ibb.co/NYmLQCF/7502-8f8188f18526d446240d148ab45b6771fc8c28ba.webp",
           "profile": "https://www.goldphoenix.de/wcf/index.php?user/2073-opklinik/"
        },
        {
           "name": "Thommy Smith",
           "rank": "Ehrenmitglied",
           "highlight": false,
           "picture": "https://www.goldphoenix.de/wcf/images/avatars/47/6833-47fdcc882ae12c898afd980c0940651ef787037c.webp",
           "profile": "https://www.goldphoenix.de/wcf/index.php?user/1831-ger-d34d-w01f/"
        },
        {
           "name": "Lukas Danger",
           "rank": "Ehrenmitglied",
           "highlight": false,
           "picture": "https://www.goldphoenix.de/wcf/images/avatars/31/7280-31648e61347062b76b2eb1c357f24fdf6b5b4368.webp",
           "profile": "https://www.goldphoenix.de/wcf/index.php?user/2024-n1gh1m4r3/"
        }
    ]
}
