{
    "members": [
        {    
            "name": "Marlon",
            "rank": "Leitung",
            "highlight": true,
            "picture": "https://www.goldphoenix.de/wcf/images/avatars/b4/6890-b4fe7f766c9471c3f83d5bbab739fdc7eee799e9.jpg",
            "profile": "https://www.goldphoenix.de/wcf/index.php?user/1773-marlon/"        
        },
        {    
            "name": "Hans Schneider",
            "rank": "Stv. Leitung",
            "highlight": true,
            "picture": "https://www.goldphoenix.de/wcf/images/avatars/d2/4088-d2b79ff7dec1d89f97bb05ea3188f3bf9548692f.jpg",
            "profile": "https://www.goldphoenix.de/wcf/index.php?user/1118-gpx-theblackarmee/"
        },
        {    
            "name": "Santos",
            "rank": "Manager",
            "highlight": true,
            "picture": "https://www.goldphoenix.de/wcf/images/avatars/5d/7248-5ddf1a14be6a01af55a682ea178727ea320839d1.jpg",
            "profile": "https://www.goldphoenix.de/wcf/index.php?user/2330-santos/"
        },
        {    
            "name": "Yasin Gholami",
            "rank": "Mitglied",
            "highlight": false,
            "picture": "https://www.goldphoenix.de/wcf/images/avatars/avatar-default.svg",
            "profile": "https://www.goldphoenix.de/wcf/index.php?user/2394-yasin/"
        },
        {    
            "name": "Adrian Monk",
            "rank": "Mitglied",
            "highlight": false,
            "picture": "https://www.goldphoenix.de/wcf/images/avatars/82/22719-8203607c210e7d19b6187ecedd6fc888d722c55a.webp",
            "profile": "https://www.goldphoenix.de/wcf/index.php?user/1652-adrian-monk/"
        },
        {
            "name": "Olli Mani",
            "rank": "Mitglied",
            "highlight": false,
            "picture": "https://www.goldphoenix.de/wcf/images/avatars/66/26480-66d4d1b657b170b04712c6ace55698899ec3ae97.jpg",
            "profile": "https://www.goldphoenix.de/wcf/index.php?user/2419-olli-mani/"
        },
        {    
            "name": "Rick Walsteen",
            "rank": "Mitglied",
            "highlight": false,
            "picture": "https://www.goldphoenix.de/wcf/images/avatars/9b/26508-9be73ee0f111ad958acb2911322d67ddb51f0ce6.jpg",
            "profile": "https://www.goldphoenix.de/wcf/index.php?user/2568-texxxxra-rick-z-walsteen/"
        },
        {    
            "name": "Rick Rich Saulus",
            "rank": "Mitglied",
            "highlight": false,
            "picture": "https://www.goldphoenix.de/wcf/images/avatars/35/26457-35c1ac542ea9025b10d246d7be829056ef973bfc.jpg",
            "profile": "https://www.goldphoenix.de/wcf/index.php?user/2296-flein/"
        }
    ]
}
