{
    "members": [
        {    
            "name": "Kaiserschmarrn",
            "rank": "Leitung",
            "highlight": true,
            "picture": "https://www.goldphoenix.de/wcf/images/avatars/30/6261-3071f34fde1e2c34cb120f2a3aa56e8afb9b788f.gif",
            "profile": "https://www.goldphoenix.de/wcf/index.php?user/1227-kaiserschmarrn/"
        },
        {    
            "name": "Anton Horvath",
            "rank": "Stv. Leitung",
            "highlight": false,
            "picture": "https://www.goldphoenix.de/wcf/images/avatars/0d/6273-0d2525a8e40758c21995b90d6c610f28615f765c.jpg",
            "profile": "https://www.goldphoenix.de/wcf/index.php?user/1697-anton-horvath/"
        },
         {    
            "name": "Lukas Kusch",
            "rank": "Manager",
            "highlight": false,
            "picture": "https://www.goldphoenix.de/wcf/images/avatars/49/6263-4960d5ed7cce6d6b86993816b3ed73d73780ca8b.jpg",
            "profile": "https://www.goldphoenix.de/wcf/index.php?user/1804-lk-sensei/"
        },
        {    
            "name": "Chrisskross",
            "rank": "Manager",
            "highlight": false,
            "picture": "https://www.goldphoenix.de/wcf/images/avatars/59/3272-5927f41840fd6c7a4b6f45fe913e08d5ad32f1cc.jpg",
            "profile": "https://www.goldphoenix.de/wcf/index.php?user/630-chrisskross/"
        },
        {    
            "name": "Marlon Brand",
            "rank": "Mitglied",
            "highlight": false,
            "picture": "https://www.goldphoenix.de/wcf/images/avatars/ac/6023-acadb5fbe6dae98d9f60eec39413239d2718933f.jpg",
            "profile": "https://www.goldphoenix.de/wcf/index.php?user/1773-marlon/"
        },
        {    
            "name": "Happy",
            "rank": "Mitglied",
            "highlight": false,
            "picture": "https://www.goldphoenix.de/wcf/images/avatars/aa/3833-aa67465593bc97e1934d0b4f22fc1ffcadedfcbe.jpg",
            "profile": "https://www.goldphoenix.de/wcf/index.php?user/456-happy/"
        },
        {
            "name": "Lennard",
            "rank": "Mitglied",
            "highlight": false,
            "picture": "https://www.goldphoenix.de/wcf/images/avatars/08/6134-0884e70fccdfab73bb2a30273c4d6fd3949ba17a.jpg",
            "profile": "https://www.goldphoenix.de/wcf/index.php?user/2016-patisto/"
        },
         {
            "name": "Heinrich Leckmann",
            "rank": "Mitglied",
            "highlight": false,
            "picture": "https://www.goldphoenix.de/wcf/images/avatars/c8/6264-c8c2cf17f8c5dc7562da23cccb7df8aaa9851054.jpg",
            "profile": "https://www.goldphoenix.de/wcf/index.php?user/1907-mr-iks/"
        },

    ]
}
