{
    "members": [      
         {
            "name": "Warthog 72",
            "rank": "General | Ausbilder",
            "highlight": true,
            "picture": "https://i.imgur.com/YcJQbSt.png",
            "profile": "https://www.goldphoenix.de/wcf/index.php?user/2010-raptic/"
        },
         {
            "name": "Nighthawk 18",
            "rank": "Generalleutnant | Ausbilder | Personalabteilung",
            "highlight": true,
            "picture": "https://www.goldphoenix.de/wcf/images/avatars/c7/6176-c7a6f60025ae06771269524a27ab7d9028d371aa.jpg",
            "profile": "https://www.goldphoenix.de/wcf/index.php?user/2024-n1gh1m4r3/"
        },
         {
            "name": "Ace 92",
            "rank": "Generalmajor",
            "highlight": false,
            "picture": "https://i.imgur.com/kRTEQ1q.png",
            "profile": "https://www.goldphoenix.de/wcf/index.php?user/1835-heinrich-danger/"
         },
         {
            "name": "Lazy 04",
            "rank": "Brigadegeneral | Ausbilder",
            "highlight": false,
            "picture": "https://i.imgur.com/N5OaIjO.png",
            "profile": "https://www.goldphoenix.de/wcf/index.php?user/1796-biglazy03/"
         },
         {
            "name": "Falcon 77",
            "rank": "Brigadegeneral | Ausbilder",
            "highlight": false,
            "picture": "https://cdn.discordapp.com/attachments/844591680342196255/908703884766249022/6541-44d1238ea7c35072f883ce9bd7a179115274cb76.png",
            "profile": "https://www.goldphoenix.de/wcf/index.php?user/1918-fake-luke/"
         },
         {
            
            "name": "Yuumi 96",
            "rank": "Hauptmann | Personalabteilung",
            "highlight": false,
            "picture": "https://www.goldphoenix.de/wcf/images/avatars/82/6533-8279e0d0653cca8b6124e43c59523a080a2f853d.png",
            "profile": "https://www.goldphoenix.de/wcf/index.php?user/1803-maxtm/"
         },
         {
            "name": "Kristall 33",
            "rank": "Oberstleutnant",
            "highlight": false,
            "picture": "https://www.goldphoenix.de/wcf/images/avatars/7c/6402-7c6ec705ff94f20e9bec370a81f8dade19adb56e.jpg",
            "profile": "https://www.goldphoenix.de/wcf/index.php?user/1667-gpx-michael-71/"         
         },
         {
            "name": "Ghost 10",
            "rank": "Oberstleutnant",
            "highlight": false,
            "picture": "https://www.goldphoenix.de/wcf/images/avatars/96/6464-966a3384357d03d904be3c8b372f0d16b50347c6.jpg",
            "profile": "https://www.goldphoenix.de/wcf/index.php?user/2101-chef-eggdog/"         
        },
        {
            "name": "Wolf 40",
            "rank": "Oberstleutnant",
            "highlight": false,
            "picture": "https://www.goldphoenix.de/wcf/images/avatars/5a/6482-5a980102edbb51b2c7928c94663261498fa679fd.jpg",
            "profile": "https://www.goldphoenix.de/wcf/index.php?user/1831-ger-d34d-w01f/"        
         },
         {
            "name": "Vigil 74",
            "rank": "Erster Leutnant",
            "highlight": false,
            "picture": "https://www.goldphoenix.de/wcf/images/avatars/7a/6449-7a7b7059ec1ae7ac6e7de4cc64e887b5dcda76bc.jpg",
            "profile": "https://www.goldphoenix.de/wcf/index.php?user/2098-reapzz/"
        },
         {
            "name": "Cerberus 30",
            "rank": "Zweiter Leutnant",
            "highlight": false,
            "picture": "https://www.goldphoenix.de/wcf/images/avatars/04/6523-044d8dbdab9a6fdc70efdcf9add15c9f2081074e.jpg",
            "profile": "https://www.goldphoenix.de/wcf/index.php?user/2109-xx-navyzeal-xx/"        
         },
         {
            "name": "Guru 34",
            "rank": "Unteroffizier",
            "highlight": false,
            "picture": "https://www.goldphoenix.de/wcf/images/avatars/38/6470-381dd18d716129d5ab1c6597470710479f1e7fb8.jpg",
            "profile": "https://www.goldphoenix.de/wcf/index.php?user/896-hpguru/"        
         },
         {
            "name": "Alpha 63",
            "rank": "Unteroffizier",
            "highlight": false,
            "picture": "https://www.goldphoenix.de/wcf/images/avatars/fb/6737-fbef849abb1af174c237513818791f81263d3525.jpg",
            "profile": "https://www.goldphoenix.de/wcf/index.php?user/2069-feinstaub/"
        },
         {
            "name": "Knight 64",
            "rank": "Unteroffizier | Personalabteilung",
            "highlight": false,
            "picture": "https://www.goldphoenix.de/wcf/images/avatars/31/6409-31945349ace9f1d979d0a5402c7d7ffce66fa903.jpg",
            "profile": "https://www.goldphoenix.de/wcf/index.php?user/2088-herrfloppy-gpx/"
        }
    ]
}
